django_youtube_thumbnail-1.0.1.dist-info/DESCRIPTION.rst
django_youtube_thumbnail-1.0.1.dist-info/METADATA
django_youtube_thumbnail-1.0.1.dist-info/metadata.json
django_youtube_thumbnail-1.0.1.dist-info/RECORD
django_youtube_thumbnail-1.0.1.dist-info/top_level.txt
django_youtube_thumbnail-1.0.1.dist-info/WHEEL
youtube_thumbnail/__init__.py
youtube_thumbnail/api.py
youtube_thumbnail/apps.py
youtube_thumbnail/migrations/0001_initial.py
youtube_thumbnail/migrations/__init__.py
youtube_thumbnail/templatetags/__init__.py
youtube_thumbnail/templatetags/__init__.pyc
youtube_thumbnail/templatetags/youtube_thumbnail.py
youtube_thumbnail/templatetags/youtube_thumbnail.pyc
youtube_thumbnail/templatetags/__pycache__/__init__.cpython-34.pyc
youtube_thumbnail/templatetags/__pycache__/youtube_thumbnail.cpython-34.pyc
